<CardContent meta:X="0" meta:Y="0" GUID="990c20fa-d68a-4639-bc9d-4edc8cb57644" xmlns:meta="Editor">
	<Root meta:RefKey="Node">a00375d2-271e-4d14-9755-980bf37583bd</Root>
	<Nodes>
		<Node meta:X="204" meta:Y="0" GUID="a00375d2-271e-4d14-9755-980bf37583bd">
			<Line>
				<MultilineString>AngrySwarmContent.Node.[0] Line.Line.MultilineString:ce11b1e2-754e-415f-8f1e-a076ee707b56</MultilineString>
			</Line>
			<Line>
				<MultilineString>AngrySwarmContent.Node.[1] Line.Line.MultilineString:7e4b7edb-3bca-4a5b-a40b-b12cb88c5df7</MultilineString>
			</Line>
			<Match3>
				<Level>AngrySwarmContentLevel</Level>
				<Success meta:RefKey="Node">abc741de-6c49-4129-ab5e-6dc19568f80d</Success>
				<Failure meta:RefKey="Node">f13f7a12-49df-4d42-8cd2-ae495fc4535e</Failure>
			</Match3>
		</Node>
		<Node meta:X="439" meta:Y="199" GUID="f13f7a12-49df-4d42-8cd2-ae495fc4535e">
			<Line>
				<MultilineString>AngrySwarmContent.Node.[0] Line.Line.MultilineString:bf81b2f3-e7ac-49bc-a7c8-15980fe5e22f</MultilineString>
			</Line>
			<MarkComplete>
				<State>Failure</State>
			</MarkComplete>
		</Node>
		<Node meta:X="476" meta:Y="0" GUID="abc741de-6c49-4129-ab5e-6dc19568f80d">
			<Line>
				<MultilineString>AngrySwarmContent.Node.[0] Line.Line.MultilineString:ebb0bfb1-a5c8-4004-a401-e022380fe592</MultilineString>
			</Line>
			<Rewards meta:RefKey="Rewards">
				<Statistics>
					<Chance>Medium</Chance>
					<Statistics meta:RefKey="Statistics">
						<Health>2</Health>
					</Statistics>
				</Statistics>
				<Statistics>
					<Chance>Medium</Chance>
					<Statistics meta:RefKey="Statistics">
						<MatchDamage>0.5</MatchDamage>
					</Statistics>
				</Statistics>
				<Statistics>
					<Chance>Medium</Chance>
					<Statistics meta:RefKey="Statistics">
						<AbilityDamage>1</AbilityDamage>
					</Statistics>
				</Statistics>
			</Rewards>
			<MarkComplete>
				<State>Success</State>
			</MarkComplete>
		</Node>
	</Nodes>
</CardContent>