<Character xmlns:meta="Editor">
	<Name>Alchemist.Character.Name:ec7de59f-b1c6-46aa-98e3-b0b77ba5d5a8</Name>
	<Description>Alchemist.Character.Description:3031baea-7d06-4e02-9988-d17cadc883fa</Description>
	<Sprite meta:RefKey="Sprite">
		<Name>Oryx/Custom/heroes/alchemist</Name>
		<DrawActualSize>true</DrawActualSize>
	</Sprite>
	<Statistics meta:RefKey="Statistics">
		<Health>8</Health>
		<AbilityDamage>1</AbilityDamage>
		<PowerGain>4</PowerGain>
	</Statistics>
	<StartingEquipment>
		<Body>Characters/Equipment/PotionBandolier</Body>
		<OffHand>Characters/Equipment/Grenade</OffHand>
	</StartingEquipment>
</Character>