<Effect xmlns:meta="Editor">
	<Loop>false</Loop>
	<Emitters>
		<Emitter>
			<Name>Thorns</Name>
			<Width>0</Width>
			<Height>0</Height>
			<SizeMultiplier>
				<Keyframe>0|1</Keyframe>
			</SizeMultiplier>
			<Direction>Up</Direction>
			<ParticleSpeed>0,0</ParticleSpeed>
			<ParticleRotation>0,0</ParticleRotation>
			<RateKeyframes>
				<Keyframe>0|1</Keyframe>
			</RateKeyframes>
			<SingleBurst>true</SingleBurst>
			<Particles>
				<Particle>
					<Lifetime>0.4,0.4</Lifetime>
					<SizeKeyframes>
						<Stream>
							<Keyframe>0|1|1</Keyframe>
							<Keyframe>0.125|0.6|0.6</Keyframe>
							<Keyframe>0.25|1|1</Keyframe>
							<Keyframe>0.375|0.6|0.6</Keyframe>
							<Keyframe>0.5|1|1</Keyframe>
							<Keyframe>0.625|0.6|0.6</Keyframe>
							<Keyframe>0.75|1|1</Keyframe>
							<Keyframe>0.875|0.6|0.6</Keyframe>
							<Keyframe>1|1|1</Keyframe>
						</Stream>
					</SizeKeyframes>
					<BlendMode>Additive</BlendMode>
					<TextureKeyframes>
						<Stream>
							<Keyframe>0|Oryx/Custom/terrain/thorns_alpha</Keyframe>
						</Stream>
					</TextureKeyframes>
					<ColourKeyframes>
						<Stream>
							<Keyframe>0|255,255,255,255</Keyframe>
						</Stream>
					</ColourKeyframes>
					<AlphaKeyframes>
						<Stream>
							<Keyframe>0|0</Keyframe>
							<Keyframe>0.1096932|1</Keyframe>
							<Keyframe>0.6036959|1</Keyframe>
							<Keyframe>0.6502092|0.8</Keyframe>
						</Stream>
					</AlphaKeyframes>
					<AlphaRefKeyframes>
						<Stream>
							<Keyframe>0|1</Keyframe>
							<Keyframe>0.4257322|0</Keyframe>
							<Keyframe>1|1</Keyframe>
						</Stream>
					</AlphaRefKeyframes>
				</Particle>
			</Particles>
		</Emitter>
	</Emitters>
</Effect>