<Effect xmlns:meta="Editor">
	<Loop>false</Loop>
	<Emitters>
		<Emitter>
			<Name>Blade</Name>
			<Shape>Cone</Shape>
			<Angle>90</Angle>
			<Width>60</Width>
			<Height>2</Height>
			<SizeMultiplier>
				<Keyframe>0|1</Keyframe>
			</SizeMultiplier>
			<Area>Border</Area>
			<ParticleSpeed>-8,-8</ParticleSpeed>
			<ParticleRotation>0,0</ParticleRotation>
			<RateKeyframes>
				<Keyframe>0|1</Keyframe>
			</RateKeyframes>
			<SingleBurst>true</SingleBurst>
			<Particles>
				<Particle>
					<Lifetime>0.25,0.25</Lifetime>
					<VelocityAligned>true</VelocityAligned>
					<SizeKeyframes>
						<Stream>
							<Keyframe>0|1|1</Keyframe>
						</Stream>
					</SizeKeyframes>
					<BlendMode>Multiplicative</BlendMode>
					<TextureKeyframes>
						<Stream>
							<Keyframe>0|Oryx/Custom/items/ataraxia_blade_flipped</Keyframe>
						</Stream>
					</TextureKeyframes>
					<ColourKeyframes>
						<Stream>
							<Keyframe>0|255,255,255,255</Keyframe>
						</Stream>
					</ColourKeyframes>
					<AlphaKeyframes>
						<Stream>
							<Keyframe>0|0</Keyframe>
							<Keyframe>0.2948669|1</Keyframe>
							<Keyframe>0.8567173|1</Keyframe>
							<Keyframe>1|0</Keyframe>
						</Stream>
					</AlphaKeyframes>
					<AlphaRefKeyframes>
						<Stream>
							<Keyframe>0|0</Keyframe>
						</Stream>
					</AlphaRefKeyframes>
				</Particle>
			</Particles>
		</Emitter>
		<Emitter>
			<Name>Debris</Name>
			<IsBlockingEmitter>false</IsBlockingEmitter>
			<Gravity>-9</Gravity>
			<Shape>Cone</Shape>
			<Angle>90</Angle>
			<Width>90</Width>
			<Height>0.1</Height>
			<SizeMultiplier>
				<Keyframe>0|1</Keyframe>
			</SizeMultiplier>
			<Offset>
				<Keyframe>0|0,-0.1</Keyframe>
			</Offset>
			<ParticleSpeed>1,3</ParticleSpeed>
			<ParticleRotation>0,360</ParticleRotation>
			<RateKeyframes>
				<Keyframe>0.2202788|20</Keyframe>
			</RateKeyframes>
			<SingleBurst>true</SingleBurst>
			<Particles>
				<Particle>
					<Lifetime>0.1,0.4</Lifetime>
					<SizeKeyframes>
						<Stream>
							<Keyframe>0|0.05|0.16</Keyframe>
						</Stream>
					</SizeKeyframes>
					<RotationSpeedKeyframes>
						<Stream>
							<Keyframe>0|-20|20</Keyframe>
						</Stream>
					</RotationSpeedKeyframes>
					<BlendMode>Multiplicative</BlendMode>
					<TextureKeyframes>
						<Stream>
							<Keyframe>0|Particle/debris1</Keyframe>
						</Stream>
						<Stream>
							<Keyframe>0|Particle/debris2</Keyframe>
						</Stream>
						<Stream>
							<Keyframe>0|Particle/debris3</Keyframe>
						</Stream>
						<Stream>
							<Keyframe>0|Particle/debris4</Keyframe>
						</Stream>
					</TextureKeyframes>
					<ColourKeyframes>
						<Stream>
							<Keyframe>0|74,52,22,255</Keyframe>
						</Stream>
					</ColourKeyframes>
					<AlphaKeyframes>
						<Stream>
							<Keyframe>0|0.5</Keyframe>
							<Keyframe>0.541635|0.5</Keyframe>
							<Keyframe>1|0</Keyframe>
						</Stream>
					</AlphaKeyframes>
					<AlphaRefKeyframes>
						<Stream>
							<Keyframe>0|0</Keyframe>
						</Stream>
					</AlphaRefKeyframes>
				</Particle>
			</Particles>
		</Emitter>
	</Emitters>
</Effect>